megaognezyum.cpython-312-x86_64-linux-musl.so
megaognezyum-1.1.dist-info/METADATA
megaognezyum-1.1.dist-info/WHEEL
megaognezyum-1.1.dist-info/top_level.txt
megaognezyum-1.1.dist-info/RECORD
megaognezyum.libs/libpcap-944fd21b.so.1.10.4
