Metadata-Version: 2.1
Name: megaognezyum
Version: 1.1
Summary: Mega Ognezyum Module with Submodules
Classifier: Programming Language :: Python :: 3
Classifier: License :: OSI Approved :: MIT License
Classifier: Operating System :: OS Independent
Requires-Python: >=3.6
